simpsons_classifier_bot/__init__.py
simpsons_classifier_bot/classifier.py
simpsons_classifier_bot/config.py
simpsons_classifier_bot/handlers.py
simpsons_classifier_bot/main.py
simpsons_classifier_bot_sheregeda-0.1.2.dist-info/LICENSE
simpsons_classifier_bot_sheregeda-0.1.2.dist-info/METADATA
simpsons_classifier_bot_sheregeda-0.1.2.dist-info/WHEEL
simpsons_classifier_bot_sheregeda-0.1.2.dist-info/top_level.txt
simpsons_classifier_bot_sheregeda-0.1.2.dist-info/RECORD
